nk100.py
nk100-1.0.0.dist-info/LICENSE
nk100-1.0.0.dist-info/METADATA
nk100-1.0.0.dist-info/WHEEL
nk100-1.0.0.dist-info/top_level.txt
nk100-1.0.0.dist-info/RECORD
