Metadata-Version: 2.2
Name: nk100
Version: 1.0.0
Summary: Layered Unicode base-100000 numeral system using Hangul, Hanja, and CJK extensions.
Home-page: https://github.com/dzbuit/nk100
Author: blueradiance
Author-email: none@example.com
Classifier: Programming Language :: Python :: 3
Classifier: License :: Other/Proprietary License
Classifier: Operating System :: OS Independent
Requires-Python: >=3.6
License-File: LICENSE
Dynamic: author
Dynamic: author-email
Dynamic: classifier
Dynamic: description
Dynamic: description-content-type
Dynamic: home-page
Dynamic: requires-python
Dynamic: summary
